env_settings/__init__.py
env_settings/env/__init__.py
env_settings/env/utils.py
django_env_settings-1.1.0.0.dist-info/METADATA
django_env_settings-1.1.0.0.dist-info/WHEEL
django_env_settings-1.1.0.0.dist-info/top_level.txt
django_env_settings-1.1.0.0.dist-info/RECORD
