Metadata-Version: 2.1
Name: django-env-settings
Version: 1.1.0.0
Summary: A set of utils for reading .env settings for django
Requires-Dist: django (>=2.1)
